potion/__init__.py
potion/client.py
potion/exceptions.py
potion/types.py
potion_sdk-1.0.0.dist-info/METADATA
potion_sdk-1.0.0.dist-info/WHEEL
potion_sdk-1.0.0.dist-info/licenses/LICENSE
potion_sdk-1.0.0.dist-info/RECORD
