Metadata-Version: 2.4
Name: potion-sdk
Version: 1.0.0
Summary: Official Python SDK for the Potion API - AI-powered beverage formulation platform
Project-URL: Homepage, https://potion.com
Project-URL: Documentation, https://potion.com/documentation
Project-URL: Repository, https://github.com/potion/potion-python
Project-URL: Changelog, https://github.com/potion/potion-python/blob/main/CHANGELOG.md
Author-email: Potion <api-support@potion.com>
License: MIT
License-File: LICENSE
Keywords: ai,api,beverage,formulation,potion,sdk
Classifier: Development Status :: 4 - Beta
Classifier: Intended Audience :: Developers
Classifier: License :: OSI Approved :: MIT License
Classifier: Operating System :: OS Independent
Classifier: Programming Language :: Python :: 3
Classifier: Programming Language :: Python :: 3.8
Classifier: Programming Language :: Python :: 3.9
Classifier: Programming Language :: Python :: 3.10
Classifier: Programming Language :: Python :: 3.11
Classifier: Programming Language :: Python :: 3.12
Classifier: Topic :: Software Development :: Libraries :: Python Modules
Classifier: Typing :: Typed
Requires-Python: >=3.8
Requires-Dist: httpx>=0.24.0
Requires-Dist: typing-extensions>=4.0.0
Provides-Extra: dev
Requires-Dist: mypy>=1.0.0; extra == 'dev'
Requires-Dist: pytest-asyncio>=0.21.0; extra == 'dev'
Requires-Dist: pytest-httpx>=0.21.0; extra == 'dev'
Requires-Dist: pytest>=7.0.0; extra == 'dev'
Requires-Dist: ruff>=0.1.0; extra == 'dev'
